Metadata-Version: 2.4
Name: snail-job-python
Version: 0.1.3
Summary: A distributed job execution framework
Project-URL: Homepage, https://gitee.com/opensnail/snail-job-python
Project-URL: Repository, https://gitee.com/opensnail/snail-job-python
Project-URL: Documentation, https://gitee.com/opensnail/snail-job-python
Author-email: dhb52 <dhb52@126.com>
License: Apache-2.0
License-File: LICENSE
Keywords: distributed,job-scheduler,retry-management,task-scheduler
Classifier: Development Status :: 4 - Beta
Classifier: Intended Audience :: Developers
Classifier: License :: OSI Approved :: Apache Software License
Classifier: Operating System :: OS Independent
Classifier: Programming Language :: Python :: 3
Classifier: Programming Language :: Python :: 3.8
Classifier: Programming Language :: Python :: 3.9
Classifier: Programming Language :: Python :: 3.10
Classifier: Programming Language :: Python :: 3.11
Classifier: Programming Language :: Python :: 3.12
Classifier: Programming Language :: Python :: 3.13
Classifier: Topic :: Software Development :: Libraries :: Python Modules
Requires-Python: >=3.8
Requires-Dist: grpcio>=1.66.2
Requires-Dist: protobuf==5.27.2
Requires-Dist: pydantic-settings>=2.0.0
Requires-Dist: pydantic>=2.7.4
Requires-Dist: requests>=2.32.3
